statsd-stubs/__init__.pyi
statsd-stubs/client/__init__.pyi
statsd-stubs/client/base.pyi
statsd-stubs/client/stream.pyi
statsd-stubs/client/timer.pyi
statsd-stubs/client/udp.pyi
statsd-stubs/defaults/__init__.pyi
statsd-stubs/defaults/django.pyi
statsd-stubs/defaults/env.pyi
statsd-stubs/py.typed
statsd_stubs-4.0.1.20240223.dist-info/LICENSE
statsd_stubs-4.0.1.20240223.dist-info/METADATA
statsd_stubs-4.0.1.20240223.dist-info/WHEEL
statsd_stubs-4.0.1.20240223.dist-info/RECORD
