Metadata-Version: 2.3
Name: statsd-stubs
Version: 4.0.1.20240223
Summary: Typing stubs for statsd
License: MIT
Keywords: statsd,types,stubs
Author: Or Levi
Author-email: orlevi128@gmail.com
Requires-Python: >=3.8,<4.0
Classifier: License :: OSI Approved :: MIT License
Classifier: Programming Language :: Python :: 3
Classifier: Programming Language :: Python :: 3.8
Classifier: Programming Language :: Python :: 3.9
Classifier: Programming Language :: Python :: 3.10
Classifier: Programming Language :: Python :: 3.11
Classifier: Programming Language :: Python :: 3.12
Classifier: Programming Language :: Python :: 3.13
Project-URL: Homepage, https://github.com/orlevii/statsd-stubs
Project-URL: Repository, https://github.com/orlevii/statsd-stubs
